windows_capture_devices.cp310-win_amd64.pyd
windows_capture_devices-1.0.0.dist-info/LICENSE
windows_capture_devices-1.0.0.dist-info/METADATA
windows_capture_devices-1.0.0.dist-info/WHEEL
windows_capture_devices-1.0.0.dist-info/top_level.txt
windows_capture_devices-1.0.0.dist-info/RECORD
